jayleneimashello/__init__.py
jayleneimashello/main.py
jayleneimashellopkg-0.0.1.dist-info/METADATA
jayleneimashellopkg-0.0.1.dist-info/WHEEL
jayleneimashellopkg-0.0.1.dist-info/top_level.txt
jayleneimashellopkg-0.0.1.dist-info/RECORD
