Metadata-Version: 2.1
Name: jayleneimashellopkg
Version: 0.0.1
Summary: Jaylen Eimas's first pip module
Home-page: UNKNOWN
Author: Jaylen Eimas First Package
Author-email: <je87794n@pace.edu>
License: UNKNOWN
Keywords: python,text,unicode
Platform: UNKNOWN
Classifier: Development Status :: 1 - Planning
Classifier: Intended Audience :: Developers
Classifier: Programming Language :: Python :: 3
Classifier: Operating System :: Unix
Classifier: Operating System :: MacOS :: MacOS X
Classifier: Operating System :: Microsoft :: Windows
Requires-Dist: wcwidth
